{
  "main": {
    "id": "3e74911a78760f5e",
    "type": "split",
    "children": [
      {
        "id": "e5d322c97176b816",
        "type": "tabs",
        "children": [
          {
            "id": "10398e074238f16e",
            "type": "leaf",
            "state": {
              "type": "markdown",
              "state": {
                "file": "Git/Git.md",
                "mode": "source",
                "source": false
              }
            }
          }
        ]
      }
    ],
    "direction": "vertical"
  },
  "left": {
    "id": "34237472763c3b5f",
    "type": "split",
    "children": [
      {
        "id": "ddf48d21d01d608d",
        "type": "tabs",
        "children": [
          {
            "id": "6f34eb7762114c64",
            "type": "leaf",
            "state": {
              "type": "file-explorer",
              "state": {
                "sortOrder": "alphabetical"
              }
            }
          },
          {
            "id": "47674ab8e95fd608",
            "type": "leaf",
            "state": {
              "type": "search",
              "state": {
                "query": "",
                "matchingCase": false,
                "explainSearch": false,
                "collapseAll": false,
                "extraContext": false,
                "sortOrder": "alphabetical"
              }
            }
          },
          {
            "id": "0511047ed8a26d13",
            "type": "leaf",
            "state": {
              "type": "starred",
              "state": {}
            }
          }
        ]
      }
    ],
    "direction": "horizontal",
    "width": 300
  },
  "right": {
    "id": "b68c2ae0f9d060f5",
    "type": "split",
    "children": [
      {
        "id": "88822e11b49f8b67",
        "type": "tabs",
        "children": [
          {
            "id": "70fa9f76db86bc4e",
            "type": "leaf",
            "state": {
              "type": "backlink",
              "state": {
                "file": "Git/Git.md",
                "collapseAll": false,
                "extraContext": false,
                "sortOrder": "alphabetical",
                "showSearch": false,
                "searchQuery": "",
                "backlinkCollapsed": false,
                "unlinkedCollapsed": true
              }
            }
          },
          {
            "id": "a24477f6bdd34c8a",
            "type": "leaf",
            "state": {
              "type": "outgoing-link",
              "state": {
                "file": "Git/Git.md",
                "linksCollapsed": false,
                "unlinkedCollapsed": true
              }
            }
          },
          {
            "id": "1ace35477f507c71",
            "type": "leaf",
            "state": {
              "type": "tag",
              "state": {
                "sortOrder": "frequency",
                "useHierarchy": true
              }
            }
          },
          {
            "id": "94e0d802fd3a1690",
            "type": "leaf",
            "state": {
              "type": "outline",
              "state": {
                "file": "Git/Git.md"
              }
            }
          }
        ]
      }
    ],
    "direction": "horizontal",
    "width": 300,
    "collapsed": true
  },
  "left-ribbon": {
    "hiddenItems": {
      "switcher:打开快速切换": false,
      "graph:查看关系图谱": false,
      "canvas:新建白板": false,
      "daily-notes:打开/创建今天的日记": false,
      "templates:插入模板": false,
      "command-palette:打开命令面板": false
    }
  },
  "active": "10398e074238f16e",
  "lastOpenFiles": [
    "Stereotype/JavaSE.md",
    "DesignPatterns/pictures/3.png"
  ]
}